{
  "spec_id": "hecbench-iso2dfd-cuda",
  "build": {
    "status": "pass",
    "duration_seconds": 1.024,
    "stdout": "rm -rf main iso2dfd.o *.bin *.txt\n\nnvcc  -std=c++17 -Xcompiler -Wall -arch=sm_89 -O3 -c iso2dfd.cu -o iso2dfd.o\nnvcc  -std=c++17 -Xcompiler -Wall -arch=sm_89 -O3 iso2dfd.o -o main \n",
    "stderr": "",
    "executable_path": "/home/samyak/Desktop/downloads/HeCBench-master/src/iso2dfd-cuda/main"
  },
  "runs": {
    "correctness": {
      "status": "pass",
      "configuration": "correctness",
      "duration_seconds": 0.138,
      "exit_code": 0,
      "stdout": "Initializing ... \nGrid Sizes: 2048 2048\nIterations: 10\n\nComputing wavefield in device ..\nRunning on:: NVIDIA GeForce RTX 4070\nThe Device Max Work Group Size is : 1024\nTotal kernel execution time 1.47852 (ms)\nAverage kernel execution time 147.852 (us)\nComputing wavefield in CPU ..\nInitializing ... \nHost time: 20 ms\n\nCheck difference between final wavefields computed in device and host\nPASS\nFinal wavefields (from device and CPU) written to disk\nFinished.  \n",
      "stderr": ""
    }
  },
  "verification": {
    "status": "pass",
    "strategy_used": "stdout_pattern",
    "details": "Pattern 'PASS' matched. Euclidean norm of GPU vs CPU wavefield below threshold"
  },
  "metrics": [
    {
      "name": "kernel_time",
      "value": 147.852,
      "unit": "us"
    }
  ]
}
