{
  "spec_id": "hecbench-softmax-online-cuda",
  "build": {
    "status": "pass",
    "duration_seconds": 3.118,
    "stdout": "rm -rf main main.o\n\nnvcc  -std=c++17 -Xcompiler -Wall -arch=sm_89 -O3 -c main.cu -o main.o\nnvcc  -std=c++17 -Xcompiler -Wall -arch=sm_89 -O3 main.o -o main \n",
    "stderr": "",
    "executable_path": "/home/samyak/Desktop/downloads/HeCBench-master/src/softmax-online-cuda/main"
  },
  "runs": {
    "correctness": {
      "status": "pass",
      "configuration": "correctness",
      "duration_seconds": 19.096,
      "exit_code": 0,
      "stdout": "Using kernel baseline 1\nLargest output is: 0.999878\nChecking block size 32.\nChecking block size 64.\nChecking block size 128.\nChecking block size 256.\nChecking block size 512.\nChecking block size 1024.\nAll results match. Starting benchmarks.\n\nblock_size   32 | time 16.1743 ms | per token 1.97 \u00b5s\nblock_size   64 | time 16.1827 ms | per token 1.98 \u00b5s\nblock_size  128 | time 16.1870 ms | per token 1.98 \u00b5s\nblock_size  256 | time 16.1881 ms | per token 1.98 \u00b5s\nblock_size  512 | time 16.2015 ms | per token 1.98 \u00b5s\nblock_size 1024 | time 16.1305 ms | per token 1.97 \u00b5s\n",
      "stderr": ""
    }
  },
  "verification": {
    "status": "pass",
    "strategy_used": "stdout_pattern",
    "details": "Pattern 'All results match' matched. validate_result() compares GPU output against CPU softmax; prints 'All results match' on success"
  },
  "metrics": [
    {
      "name": "kernel_time",
      "value": 16.1743,
      "unit": "ms"
    }
  ]
}
